setup.py
jeff/__init__.py
jeff/jeff.py
jeff.egg-info/PKG-INFO
jeff.egg-info/SOURCES.txt
jeff.egg-info/dependency_links.txt
jeff.egg-info/entry_points.txt
jeff.egg-info/requires.txt
jeff.egg-info/top_level.txt
jeff/licenses/afl-3.0
jeff/licenses/agpl-3.0
jeff/licenses/apache-2.0
jeff/licenses/artistic-2.0
jeff/licenses/bsd-2-clause
jeff/licenses/bsd-3-clause
jeff/licenses/bsd-3-clause-clear
jeff/licenses/cc0-1.0
jeff/licenses/epl-1.0
jeff/licenses/gpl-2.0
jeff/licenses/gpl-3.0
jeff/licenses/isc
jeff/licenses/lgpl-2.1
jeff/licenses/lgpl-3.0
jeff/licenses/mit
jeff/licenses/mpl-2.0
jeff/licenses/ms-pl
jeff/licenses/ms-rl
jeff/licenses/no-license
jeff/licenses/ofl-1.1
jeff/licenses/osl-3.0
jeff/licenses/unlicense
jeff/licenses/wtfpl