Metadata-Version: 1.1
Name: jeff
Version: 0.3.0
Summary: Jeff generates license file from the command line.
Home-page: https://github.com/oskarcieslik/Jeff
Author: Oskar Cieslik
Author-email: oskar.cieslik@gmail.com
License: MIT
Download-URL: https://github.com/oskarcieslik/Jeff
Keywords: license,github,python,command line,cli
Platform: UNKNOWN
